[
  {
    "County":"Allegany",
    "Number":15
  },
  {
    "County":"Anne Arundel",
    "Number":78
  },
  {
    "County":"Baltimore City",
    "Number":246
  },
  {
    "County":"Baltimore County",
    "Number":144
  },
  {
    "County":"Calvert",
    "Number":6
  },
  {
    "County":"Caroline",
    "Number":2
  },
  {
    "County":"Carroll",
    "Number":24
  },
  {
    "County":"Cecil",
    "Number":26
  },
  {
    "County":"Charles",
    "Number":9
  },
  {
    "County":"Dorchester",
    "Number":5
  },
  {
    "County":"Frederick",
    "Number":37
  },
  {
    "County":"Garrett",
    "Number":6
  },
  {
    "County":"Harford",
    "Number":36
  },
  {
    "County":"Howard",
    "Number":29
  },
  {
    "County":"Kent",
    "Number":4
  },
  {
    "County":"Montgomery",
    "Number":52
  },
  {
    "County":"Prince George's",
    "Number":59
  },
  {
    "County":"Queen Anne's",
    "Number":8
  },
  {
    "County":"Somerset",
    "Number":4
  },
  {
    "County":"St. Mary's",
    "Number":10
  },
  {
    "County":"Talbot",
    "Number":7
  },
  {
    "County":"Washington",
    "Number":28
  },
  {
    "County":"Wicomico",
    "Number":17
  },
  {
    "County":"Worcester",
    "Number":6
  },
  {
    "County":"MARYLAND",
    "Number":858
  }
]